{
  "word": "affection",
  "phonetic": "/əˈfɛkʃən/",
  "pos": [
    "noun",
    "verb"
  ],
  "selected_pos": "noun",
  "definition": "喜爱；爱慕；感情",
  "examples": [
    {
      "sentence": "The governor expressed deep affection for his hometown in his farewell address.",
      "style": "Formal",
      "translation": "州长在告别演讲中表达了对家乡的深厚感情。",
      "translated_word": "感情",
      "display_order": 4
    },
    {
      "sentence": "Affection is a gentle feeling of fondness and care toward someone or something.",
      "style": "Definitional",
      "translation": "喜爱是一种对某人或某物温柔的喜欢和关心之情。",
      "translated_word": "喜爱",
      "display_order": null
    },
    {
      "sentence": "Unlike passion, which burns intensely, affection grows slowly and lasts longer.",
      "style": "Contrastive",
      "translation": "与强烈燃烧的激情不同，喜爱是慢慢滋长且更为持久的。",
      "translated_word": "喜爱",
      "display_order": 2
    },
    {
      "sentence": "The old couple showed affection for each other through small daily gestures.",
      "style": "Collocational",
      "translation": "这对老夫妻通过日常的小举动表达彼此的爱意。",
      "translated_word": "爱意",
      "display_order": 1
    },
    {
      "sentence": "True affection asks for nothing in return; it simply exists.",
      "style": "Philosophical",
      "translation": "真正的爱不求回报，它只是自然存在。",
      "translated_word": "爱",
      "display_order": null
    },
    {
      "sentence": "Her affection bloomed like spring flowers, quiet yet impossible to ignore.",
      "style": "Poetic",
      "translation": "她的爱意如春花般绽放，静谧却无法忽视。",
      "translated_word": "爱意",
      "display_order": 3
    },
    {
      "sentence": "Never be afraid to show affection; the world needs more warmth.",
      "style": "Inspirational",
      "translation": "永远不要害怕表达爱意，这个世界需要更多温暖。",
      "translated_word": "爱意",
      "display_order": null
    }
  ]
}
