{
  "word": "abolish",
  "phonetic": "/əˈbɒlɪʃ/",
  "pos": [
    "verb"
  ],
  "selected_pos": "verb",
  "definition": "废除；取消；废止",
  "examples": [
    {
      "sentence": "The government voted to abolish the outdated tax policy.",
      "style": "Formal",
      "translation": "政府投票决定废除这项过时的税收政策。",
      "translated_word": "废除",
      "display_order": null
    },
    {
      "sentence": "To abolish means to officially end a law, practice, or institution.",
      "style": "Definitional",
      "translation": "abolish指正式终结某项法律、惯例或制度。",
      "translated_word": "abolish",
      "display_order": null
    },
    {
      "sentence": "Unlike merely reforming a system, abolishing it removes it entirely.",
      "style": "Contrastive",
      "translation": "与仅仅改革制度不同，废除意味着彻底消除它。",
      "translated_word": "废除",
      "display_order": 2
    },
    {
      "sentence": "The movement sought to abolish slavery and grant freedom to all.",
      "style": "Collocational",
      "translation": "这场运动旨在废除奴隶制，赋予所有人自由。",
      "translated_word": "废除",
      "display_order": 1
    },
    {
      "sentence": "Can progress exist without abolishing the traditions that once shaped society?",
      "style": "Philosophical",
      "translation": "不废除曾经塑造社会的传统，进步还能存在吗？",
      "translated_word": "废除",
      "display_order": 4
    },
    {
      "sentence": "Time abolishes empires as softly as dusk erases the horizon.",
      "style": "Poetic",
      "translation": "时间消解帝国，如同黄昏悄然抹去天际线。",
      "translated_word": "消解",
      "display_order": null
    },
    {
      "sentence": "Every generation holds the power to abolish injustice and rewrite the future.",
      "style": "Inspirational",
      "translation": "每一代人都有力量废除不公，重写未来。",
      "translated_word": "废除",
      "display_order": 3
    }
  ]
}
