{
  "word": "concede",
  "phonetic": "/kənˈsiːd/",
  "pos": [
    "verb"
  ],
  "selected_pos": "verb",
  "definition": "承认；让步；认输",
  "examples": [
    {
      "sentence": "The senator conceded defeat after the final votes were counted.",
      "style": "Formal",
      "translation": "在最终计票结束后，这位参议员承认了败选。",
      "translated_word": "承认",
      "display_order": 2
    },
    {
      "sentence": "To concede means to acknowledge something reluctantly as true or valid.",
      "style": "Definitional",
      "translation": "Concede的意思是不情愿地承认某事为真或有效。",
      "translated_word": "承认",
      "display_order": null
    },
    {
      "sentence": "Unlike denying the obvious, choosing to concede shows intellectual honesty.",
      "style": "Contrastive",
      "translation": "与否认显而易见的事实不同，选择承认彰显了理性诚实。",
      "translated_word": "承认",
      "display_order": null
    },
    {
      "sentence": "The coach had to concede defeat and congratulate the opposing team.",
      "style": "Collocational",
      "translation": "教练不得不认输，并向对方球队表示祝贺。",
      "translated_word": "认输",
      "display_order": null
    },
    {
      "sentence": "To concede a point in debate is not weakness; it is the mark of a mind open to truth.",
      "style": "Philosophical",
      "translation": "在辩论中承认对方的观点并非软弱，而是心胸开放、追求真理的表现。",
      "translated_word": "承认",
      "display_order": 3
    },
    {
      "sentence": "Even the stubborn winter must concede to the gentle warmth of spring.",
      "style": "Poetic",
      "translation": "即便是顽固的寒冬，也终须向春日的暖意让步。",
      "translated_word": "让步",
      "display_order": 1
    },
    {
      "sentence": "Never concede your dreams to fear; let courage be your guide.",
      "style": "Inspirational",
      "translation": "永远不要向恐惧屈服而放弃梦想，让勇气成为你的向导。",
      "translated_word": "屈服",
      "display_order": 4
    }
  ]
}
