{
  "word": "grouchy",
  "phonetic": "/ˈɡraʊtʃi/",
  "pos": [
    "adjective"
  ],
  "selected_pos": "adjective",
  "definition": "暴躁的；易怒的；脾气坏的",
  "examples": [
    {
      "sentence": "Don't mind him; he gets grouchy when he's hungry.",
      "style": "Contextual",
      "translation": "别介意他，饿的时候他就容易发脾气。",
      "translated_word": "发脾气",
      "display_order": 1
    },
    {
      "sentence": "Even the grouchy old cat purred in the afternoon sun.",
      "style": "Collocational",
      "translation": "连那只脾气暴躁的老猫也在午后的阳光下打起了呼噜。",
      "translated_word": "脾气暴躁",
      "display_order": 4
    },
    {
      "sentence": "Mornings made me grouchy until you started leaving notes by the kettle.",
      "style": "Intimate",
      "translation": "清晨总让我烦躁不安，直到你开始在水壶旁留下纸条。",
      "translated_word": "烦躁不安",
      "display_order": 3
    },
    {
      "sentence": "He looked grouchy, but his eyes softened when the child waved.",
      "style": "Contrastive",
      "translation": "他看起来脾气很坏，但当孩子挥手时，他的眼神柔和了下来。",
      "translated_word": "脾气很坏",
      "display_order": 2
    }
  ]
}