[
  {
    "word": "chopper",
    "phonetic": "/ˈtʃɔp.ə/",
    "pos": [
      "noun",
      "verb"
    ],
    "selected_pos": "noun",
    "definition": "直升机；砍刀；切碎器",
    "examples": [
      {
        "sentence": "Like a chopper rising above the storm, you have the power to lift yourself above any challenge.",
        "style": "Inspirational",
        "translation": "就像一架直升机在风暴中升空，你有能力让自己超越任何挑战。",
        "translated_word": "直升机"
      },
      {
        "sentence": "The chopper reminds us that perspective changes everything; from above, even mountains look small.",
        "style": "Philosophical",
        "translation": "直升机提醒我们视角改变一切：从高处看，即使是山脉也显得渺小。",
        "translated_word": "直升机"
      },
      {
        "sentence": "The chopper hums through twilight skies, a dragonfly of steel carrying dreams homeward.",
        "style": "Poetic",
        "translation": "直升机在暮色中嗡嗡飞过，一只钢铁蜻蜓载着梦想归家。",
        "translated_word": "直升机"
      },
      {
        "sentence": "A rescue chopper arrived at the scene within minutes and airlifted the injured hiker to safety.",
        "style": "News-like",
        "translation": "一架救援直升机在几分钟内抵达现场，将受伤的登山者空运至安全地点。",
        "translated_word": "直升机"
      }
    ]
  },
  {
    "word": "adherence",
    "phonetic": null,
    "pos": [
      "noun"
    ],
    "selected_pos": "noun",
    "definition": "坚持；遵守；忠诚",
    "examples": [
      {
        "sentence": "Your adherence to your dreams, even when the path grows dark, is what separates the hopeful from the hopeless.",
        "style": "Inspirational",
        "translation": "即使道路变得黑暗，你对梦想的坚持正是区分希望者与绝望者的关键。",
        "translated_word": "坚持"
      },
      {
        "sentence": "True freedom lies not in the absence of rules, but in the conscious adherence to principles we choose for ourselves.",
        "style": "Philosophical",
        "translation": "真正的自由不在于没有规则，而在于自觉遵守我们为自己选择的原则。",
        "translated_word": "遵守"
      },
      {
        "sentence": "Like a river's faithful adherence to its ancient course, love finds its way through stone and season.",
        "style": "Poetic",
        "translation": "如同河流对古老河道的忠诚，爱穿越岩石与季节寻找它的道路。",
        "translated_word": "忠诚"
      },
      {
        "sentence": "The company's strict adherence to safety protocols prevented what could have been a major industrial accident.",
        "style": "News-like",
        "translation": "该公司对安全规程的严格遵守避免了一场可能发生的重大工业事故。",
        "translated_word": "遵守"
      }
    ]
  },
  {
    "word": "showdown",
    "phonetic": null,
    "pos": [
      "noun"
    ],
    "selected_pos": "noun",
    "definition": "摊牌；最终对决；决战",
    "examples": [
      {
        "sentence": "Every showdown in life is an opportunity to prove what you're truly made of.",
        "style": "Inspirational",
        "translation": "人生中的每一次摊牌都是证明你真正实力的机会。",
        "translated_word": "摊牌"
      },
      {
        "sentence": "The showdown between truth and illusion reveals which foundations we have built our lives upon.",
        "style": "Philosophical",
        "translation": "真相与幻象之间的对决揭示了我们生命建立在何种根基之上。",
        "translated_word": "对决"
      },
      {
        "sentence": "At twilight's edge, the showdown of sun and moon paints the sky in gold and silver.",
        "style": "Poetic",
        "translation": "在黄昏的边缘，日月的决战将天空染成金银交织。",
        "translated_word": "决战"
      },
      {
        "sentence": "The trade negotiations are heading toward a showdown as both sides refuse to compromise.",
        "style": "News-like",
        "translation": "由于双方都拒绝妥协，贸易谈判正走向最终摊牌。",
        "translated_word": "摊牌"
      }
    ]
  },
  {
    "word": "rehab",
    "phonetic": "/ˈɹiːhæb/",
    "pos": [
      "noun",
      "verb"
    ],
    "selected_pos": "noun",
    "definition": "康复中心；戒毒所；康复治疗",
    "examples": [
      {
        "sentence": "Rehab is not a sign of weakness; it is the first step toward reclaiming your life.",
        "style": "Inspirational",
        "translation": "康复治疗不是软弱的表现，而是重新掌控人生的第一步。",
        "translated_word": "康复治疗"
      },
      {
        "sentence": "In rehab, we confront not just addiction, but the emptiness we tried to fill.",
        "style": "Philosophical",
        "translation": "在康复中心，我们面对的不仅是成瘾，还有我们试图填补的空虚。",
        "translated_word": "康复中心"
      },
      {
        "sentence": "Rehab is a garden where broken souls learn to bloom again in gentle sunlight.",
        "style": "Poetic",
        "translation": "康复中心是一座花园，破碎的灵魂在柔和的阳光下学会重新绽放。",
        "translated_word": "康复中心"
      },
      {
        "sentence": "The singer checked into rehab last week after canceling her world tour.",
        "style": "News-like",
        "translation": "这位歌手在取消世界巡演后于上周住进了戒毒所。",
        "translated_word": "戒毒所"
      }
    ]
  },
  {
    "word": "traction",
    "phonetic": "/ˈtɹæk.ʃən/",
    "pos": [
      "noun",
      "verb"
    ],
    "selected_pos": "noun",
    "definition": "牵引力；进展；支持",
    "examples": [
      {
        "sentence": "Every small win builds traction, propelling you closer to the life you've always envisioned.",
        "style": "Inspirational",
        "translation": "每一个小小的胜利都在积累动力，推动你更接近心中向往的生活。",
        "translated_word": "动力"
      },
      {
        "sentence": "Ideas gain traction not through force, but through the quiet persistence of those who believe in them.",
        "style": "Philosophical",
        "translation": "思想获得支持，不是靠强迫，而是靠信仰者的默默坚持。",
        "translated_word": "支持"
      },
      {
        "sentence": "Like roots seeking water, her dreams found traction in the fertile soil of hope.",
        "style": "Poetic",
        "translation": "如同根须寻觅水源，她的梦想在希望的沃土中找到了立足之地。",
        "translated_word": "立足之地"
      },
      {
        "sentence": "The startup's new app is gaining traction among young professionals in major cities.",
        "style": "News-like",
        "translation": "这家初创公司的新应用正在各大城市的年轻职场人士中获得关注。",
        "translated_word": "关注"
      }
    ]
  },
  {
    "word": "scientifically",
    "phonetic": null,
    "pos": [
      "adverb"
    ],
    "selected_pos": "adverb",
    "definition": "科学地；按科学方法地",
    "examples": [
      {
        "sentence": "When you approach your goals scientifically, even the impossible becomes a series of achievable steps.",
        "style": "Inspirational",
        "translation": "当你用科学的方法对待目标时，即使是不可能的事也会变成一系列可实现的步骤。",
        "translated_word": "科学的方法"
      },
      {
        "sentence": "To think scientifically is to accept that our deepest beliefs must bow before evidence.",
        "style": "Philosophical",
        "translation": "科学地思考意味着承认我们最深刻的信念必须在证据面前低头。",
        "translated_word": "科学地"
      },
      {
        "sentence": "The stars arrange themselves scientifically, yet their beauty speaks in the language of dreams.",
        "style": "Poetic",
        "translation": "星辰按科学规律排列，却用梦的语言诉说着美丽。",
        "translated_word": "按科学规律"
      },
      {
        "sentence": "The new vaccine has been scientifically proven to reduce infection rates by over sixty percent.",
        "style": "News-like",
        "translation": "这款新疫苗已被科学证明能将感染率降低百分之六十以上。",
        "translated_word": "科学证明"
      }
    ]
  },
  {
    "word": "lame",
    "phonetic": "/leɪm/",
    "pos": [
      "adjective",
      "noun",
      "verb"
    ],
    "selected_pos": "adjective",
    "definition": "跛的；蹩脚的；无说服力的",
    "examples": [
      {
        "sentence": "Don't let a lame excuse stop you from chasing your dreams.",
        "style": "Inspirational",
        "translation": "不要让蹩脚的借口阻止你追逐梦想。",
        "translated_word": "蹩脚的"
      },
      {
        "sentence": "Every lame argument reveals more about the speaker than the subject.",
        "style": "Philosophical",
        "translation": "每一个无力的论点都更多地暴露了说话者本身，而非论题。",
        "translated_word": "无力的"
      },
      {
        "sentence": "The lame bird still sings, its voice unbroken by wounded wings.",
        "style": "Poetic",
        "translation": "那只跛足的鸟依然歌唱，受伤的翅膀未能折断它的歌声。",
        "translated_word": "跛足的"
      },
      {
        "sentence": "That's such a lame excuse; just admit you forgot my birthday.",
        "style": "Conversational",
        "translation": "那真是个蹩脚的借口，承认你忘了我生日就好了。",
        "translated_word": "蹩脚的"
      }
    ]
  },
  {
    "word": "journalistic",
    "phonetic": "/ˌd͡ʒɜː(ɹ)nəˈlɪstɪk/",
    "pos": [
      "adjective"
    ],
    "selected_pos": "adjective",
    "definition": "新闻的；新闻工作的；新闻业的",
    "examples": [
      {
        "sentence": "Her journalistic courage to expose corruption inspired an entire generation of young reporters to pursue truth fearlessly.",
        "style": "Inspirational",
        "translation": "她揭露腐败的新闻勇气激励了整整一代年轻记者无畏地追求真相。",
        "translated_word": "新闻"
      },
      {
        "sentence": "The journalistic pursuit of objectivity raises a profound question: can any observer truly separate fact from interpretation?",
        "style": "Philosophical",
        "translation": "新闻业对客观性的追求引发了一个深刻的问题：观察者真的能将事实与诠释分离吗？",
        "translated_word": "新闻业"
      },
      {
        "sentence": "His journalistic lens captured not just events, but the silent poetry of lives unfolding in forgotten corners of the world.",
        "style": "Poetic",
        "translation": "他的新闻镜头捕捉的不仅是事件，还有世界被遗忘角落里生命静静展开的诗意。",
        "translated_word": "新闻"
      },
      {
        "sentence": "The documentary won praise for its rigorous journalistic standards and thorough investigation of the financial scandal.",
        "style": "News-like",
        "translation": "这部纪录片因其严格的新闻标准和对金融丑闻的彻底调查而获得赞誉。",
        "translated_word": "新闻"
      }
    ]
  },
  {
    "word": "re-establish",
    "phonetic": null,
    "pos": [
      "verb"
    ],
    "selected_pos": "verb",
    "definition": "重建；恢复；重新建立",
    "examples": [
      {
        "sentence": "It is never too late to re-establish trust with someone you have hurt.",
        "style": "Inspirational",
        "translation": "重建与你伤害过的人之间的信任，永远不会太晚。",
        "translated_word": "重建"
      },
      {
        "sentence": "To re-establish order, one must first understand the nature of chaos.",
        "style": "Philosophical",
        "translation": "要恢复秩序，必须先理解混乱的本质。",
        "translated_word": "恢复"
      },
      {
        "sentence": "Spring returns to re-establish its gentle reign over the sleeping earth.",
        "style": "Poetic",
        "translation": "春天归来，重新建立它对沉睡大地的温柔统治。",
        "translated_word": "重新建立"
      },
      {
        "sentence": "The two countries are working to re-establish diplomatic relations after decades of tension.",
        "style": "News-like",
        "translation": "经过数十年的紧张关系，两国正在努力恢复外交关系。",
        "translated_word": "恢复"
      }
    ]
  },
  {
    "word": "analog",
    "phonetic": "/ˈæ.nə.lɑɡ/",
    "pos": [
      "adjective",
      "noun"
    ],
    "selected_pos": "noun",
    "definition": "类似物；相似体；模拟信号",
    "examples": [
      {
        "sentence": "Every struggle you face is an analog of the battles others have conquered before you.",
        "style": "Inspirational",
        "translation": "你面对的每一次挣扎都是他人曾经征服过的战斗的类似物。",
        "translated_word": "类似物"
      },
      {
        "sentence": "Is memory an analog of reality, or does it create a truth entirely its own?",
        "style": "Philosophical",
        "translation": "记忆是现实的相似体，还是它创造了一个完全属于自己的真相？",
        "translated_word": "相似体"
      },
      {
        "sentence": "The river is an analog of time: both flow forward, never pausing, never returning.",
        "style": "Poetic",
        "translation": "河流是时间的类比：两者都向前流淌，从不停歇，从不回头。",
        "translated_word": "类比"
      },
      {
        "sentence": "Some photographers still prefer shooting on analog because it captures light differently than digital.",
        "style": "Conversational",
        "translation": "一些摄影师仍然喜欢用模拟设备拍摄，因为它捕捉光线的方式和数码不同。",
        "translated_word": "模拟设备"
      }
    ]
  },
  {
    "word": "parrot",
    "phonetic": "/ˈpæɹət/",
    "pos": [
      "noun",
      "verb"
    ],
    "selected_pos": "noun",
    "definition": "鹦鹉",
    "examples": [
      {
        "sentence": "Like a parrot learning to speak, we must repeat our affirmations until they become our truth.",
        "style": "Inspirational",
        "translation": "就像鹦鹉学说话一样，我们必须不断重复自我肯定，直到它们成为我们的真理。",
        "translated_word": "鹦鹉"
      },
      {
        "sentence": "The parrot mimics words without understanding; how often do we do the same with ideas we never question?",
        "style": "Philosophical",
        "translation": "鹦鹉模仿话语却不理解其意；我们又有多少次对从未质疑的观念做着同样的事？",
        "translated_word": "鹦鹉"
      },
      {
        "sentence": "A parrot of emerald and gold perched silent, holding secrets of the rainforest in its ancient eyes.",
        "style": "Poetic",
        "translation": "一只翠绿金黄的鹦鹉静静栖息，古老的眼眸中藏着雨林的秘密。",
        "translated_word": "鹦鹉"
      },
      {
        "sentence": "My neighbor's parrot has learned to imitate the doorbell, and now nobody knows when there's actually a visitor.",
        "style": "Conversational",
        "translation": "我邻居的鹦鹉学会了模仿门铃声，现在没人知道是不是真的有客人来了。",
        "translated_word": "鹦鹉"
      }
    ]
  },
  {
    "word": "template",
    "phonetic": "/ˈtɛm.pleɪt/",
    "pos": [
      "noun",
      "verb"
    ],
    "selected_pos": "noun",
    "definition": "模板；范本；样板",
    "examples": [
      {
        "sentence": "Let your failures become a template for growth, not a blueprint for defeat.",
        "style": "Inspirational",
        "translation": "让你的失败成为成长的模板，而非失败的蓝图。",
        "translated_word": "模板"
      },
      {
        "sentence": "Is free will an illusion, or are we simply following a template written by nature and nurture?",
        "style": "Philosophical",
        "translation": "自由意志是幻觉，还是我们只是在遵循由天性与教养书写的范本？",
        "translated_word": "范本"
      },
      {
        "sentence": "The autumn leaf drifts down, a golden template of seasons past, whispering of time.",
        "style": "Poetic",
        "translation": "秋叶飘落，如一片金色的模板，低语着逝去的时光。",
        "translated_word": "模板"
      },
      {
        "sentence": "I found a great template online for the resume; it saved me hours of formatting.",
        "style": "Conversational",
        "translation": "我在网上找到了一个很棒的简历模板，省了我好几个小时的排版时间。",
        "translated_word": "模板"
      }
    ]
  },
  {
    "word": "deserted",
    "phonetic": "/dɪˈzɜːtəd/",
    "pos": [
      "adjective",
      "verb"
    ],
    "selected_pos": "adjective",
    "definition": "荒芜的；被遗弃的；空无一人的",
    "examples": [
      {
        "sentence": "Even in the most deserted places, hope can bloom if you plant the seeds of perseverance.",
        "style": "Inspirational",
        "translation": "即使在最荒芜的地方，只要播下坚持的种子，希望也能绽放。",
        "translated_word": "荒芜的"
      },
      {
        "sentence": "A deserted street at midnight reveals truths that crowded places keep hidden.",
        "style": "Philosophical",
        "translation": "午夜空无一人的街道揭示了拥挤之处隐藏的真相。",
        "translated_word": "空无一人的"
      },
      {
        "sentence": "The deserted lighthouse stood silent, a lonely sentinel whispering secrets to the wandering waves.",
        "style": "Poetic",
        "translation": "那座被遗弃的灯塔静默伫立，像孤独的哨兵向漂泊的波浪低语秘密。",
        "translated_word": "被遗弃的"
      },
      {
        "sentence": "The once bustling mall now sits completely deserted after the new shopping center opened nearby.",
        "style": "News-like",
        "translation": "自从附近新购物中心开业后，这座曾经繁华的商场如今已完全荒废。",
        "translated_word": "荒废"
      }
    ]
  },
  {
    "word": "faulty",
    "phonetic": "/ˈfɔːlti/",
    "pos": [
      "adjective"
    ],
    "selected_pos": "adjective",
    "definition": "有缺陷的；有毛病的；不完善的",
    "examples": [
      {
        "sentence": "A faulty start does not determine your finish; every setback is a setup for a comeback.",
        "style": "Inspirational",
        "translation": "一个有缺陷的开始并不能决定你的结局；每一次挫折都是为东山再起做准备。",
        "translated_word": "有缺陷的"
      },
      {
        "sentence": "Perhaps our faulty perceptions of reality reveal more truth than perfect clarity ever could.",
        "style": "Philosophical",
        "translation": "也许我们对现实不完善的感知比完美的清晰更能揭示真相。",
        "translated_word": "不完善的"
      },
      {
        "sentence": "Like a faulty compass spinning in the storm, my heart searched for a direction home.",
        "style": "Poetic",
        "translation": "如同一个在风暴中旋转的有毛病的指南针，我的心寻找着回家的方向。",
        "translated_word": "有毛病的"
      },
      {
        "sentence": "The company recalled thousands of vehicles due to faulty brake systems.",
        "style": "News-like",
        "translation": "该公司因刹车系统存在缺陷而召回了数千辆汽车。",
        "translated_word": "存在缺陷"
      }
    ]
  },
  {
    "word": "unification",
    "phonetic": null,
    "pos": [
      "noun"
    ],
    "selected_pos": "noun",
    "definition": "统一；联合；合并",
    "examples": [
      {
        "sentence": "The unification of our efforts will lead us to achievements we could never reach alone.",
        "style": "Inspirational",
        "translation": "我们努力的统一将带领我们实现独自永远无法达成的成就。",
        "translated_word": "统一"
      },
      {
        "sentence": "True unification begins not with shared borders, but with shared understanding.",
        "style": "Philosophical",
        "translation": "真正的统一不是始于共同的边界，而是始于共同的理解。",
        "translated_word": "统一"
      },
      {
        "sentence": "Like rivers merging into the sea, unification is nature's quiet symphony of becoming whole.",
        "style": "Poetic",
        "translation": "如同河流汇入大海，统一是大自然悄然奏响的完整交响曲。",
        "translated_word": "统一"
      },
      {
        "sentence": "The unification of the two companies will create the largest tech firm in the region.",
        "style": "News-like",
        "translation": "两家公司的合并将创建该地区最大的科技企业。",
        "translated_word": "合并"
      }
    ]
  },
  {
    "word": "thump",
    "phonetic": "/θʌmp/",
    "pos": [
      "noun",
      "verb"
    ],
    "selected_pos": "verb",
    "definition": "重击；砰砰跳；怦怦作响",
    "examples": [
      {
        "sentence": "Let your heart thump with excitement as you chase your wildest dreams.",
        "style": "Inspirational",
        "translation": "当你追逐最狂野的梦想时，让你的心怦怦跳动吧。",
        "translated_word": "怦怦跳动"
      },
      {
        "sentence": "We thump against the walls of our limitations, never knowing which blow will break them down.",
        "style": "Philosophical",
        "translation": "我们不断撞击自身局限的围墙，却永远不知道哪一击会将其击溃。",
        "translated_word": "撞击"
      },
      {
        "sentence": "Rain thumps upon the old tin roof like a thousand gentle drummers playing through the night.",
        "style": "Poetic",
        "translation": "雨点敲打着古老的铁皮屋顶，如同千名轻柔的鼓手彻夜演奏。",
        "translated_word": "敲打"
      },
      {
        "sentence": "I could hear my neighbor thumping around upstairs at three in the morning.",
        "style": "Conversational",
        "translation": "我能听到邻居凌晨三点在楼上咚咚走来走去。",
        "translated_word": "咚咚走来走去"
      }
    ]
  },
  {
    "word": "paralysis",
    "phonetic": "/pəˈɹæləsəs/",
    "pos": [
      "noun"
    ],
    "selected_pos": "noun",
    "definition": "瘫痪；麻痹；停滞",
    "examples": [
      {
        "sentence": "The paralysis of fear is temporary; your courage to move forward is permanent.",
        "style": "Inspirational",
        "translation": "恐惧带来的麻痹是暂时的，而你向前迈进的勇气是永恒的。",
        "translated_word": "麻痹"
      },
      {
        "sentence": "In the paralysis of indecision, we discover that choosing nothing is still a choice.",
        "style": "Philosophical",
        "translation": "在犹豫不决的停滞中，我们发现不做选择本身也是一种选择。",
        "translated_word": "停滞"
      },
      {
        "sentence": "Winter holds the garden in gentle paralysis, waiting for spring's awakening touch.",
        "style": "Poetic",
        "translation": "冬天将花园轻柔地锁在沉寂之中，等待春天唤醒的触碰。",
        "translated_word": "沉寂"
      },
      {
        "sentence": "The sudden power outage caused complete paralysis of the city's subway system during rush hour.",
        "style": "News-like",
        "translation": "突发停电导致该市地铁系统在高峰时段完全瘫痪。",
        "translated_word": "瘫痪"
      }
    ]
  },
  {
    "word": "strew",
    "phonetic": "/stɹuː/",
    "pos": [
      "verb"
    ],
    "selected_pos": "verb",
    "definition": "撒；散布；铺满",
    "examples": [
      {
        "sentence": "Strew kindness wherever you go, and watch how the world blossoms around you.",
        "style": "Inspirational",
        "translation": "无论走到哪里都撒下善意，看着世界在你身边绽放。",
        "translated_word": "撒下"
      },
      {
        "sentence": "We strew our days with choices, yet rarely pause to consider what we are planting.",
        "style": "Philosophical",
        "translation": "我们用选择铺满每一天，却很少停下来思考自己在播种什么。",
        "translated_word": "铺满"
      },
      {
        "sentence": "Autumn winds strew golden leaves like whispered secrets across the sleeping earth.",
        "style": "Poetic",
        "translation": "秋风将金黄的落叶如低语的秘密般散落在沉睡的大地上。",
        "translated_word": "散落"
      },
      {
        "sentence": "The kids helped strew flower petals along the aisle before the wedding ceremony.",
        "style": "Conversational",
        "translation": "婚礼仪式前，孩子们帮忙在过道上撒花瓣。",
        "translated_word": "撒"
      }
    ]
  },
  {
    "word": "tempo",
    "phonetic": "/ˈtɛm.pəʊ/",
    "pos": [
      "noun"
    ],
    "selected_pos": "noun",
    "definition": "节奏；速度；拍子",
    "examples": [
      {
        "sentence": "Find your own tempo in life, and don't let others rush your journey to greatness.",
        "style": "Inspirational",
        "translation": "找到你自己人生的节奏，不要让别人催促你走向伟大的旅程。",
        "translated_word": "节奏"
      },
      {
        "sentence": "The tempo of existence reveals itself not in speed, but in the spaces between moments.",
        "style": "Philosophical",
        "translation": "存在的节奏不在于速度，而在于时刻之间的留白中显现。",
        "translated_word": "节奏"
      },
      {
        "sentence": "The rain fell in a gentle tempo, composing lullabies upon the ancient rooftops.",
        "style": "Poetic",
        "translation": "雨以轻柔的节拍落下，在古老的屋顶上谱写着摇篮曲。",
        "translated_word": "节拍"
      },
      {
        "sentence": "The conductor increased the tempo during the finale, bringing the audience to their feet.",
        "style": "News-like",
        "translation": "指挥在终曲时加快了速度，观众们纷纷起立。",
        "translated_word": "速度"
      }
    ]
  },
  {
    "word": "acquit",
    "phonetic": "/əˈkwɪt/",
    "pos": [
      "verb"
    ],
    "selected_pos": "verb",
    "definition": "宣判无罪；表现",
    "examples": [
      {
        "sentence": "When life puts you on trial, acquit yourself with courage and let your actions speak louder than accusations.",
        "style": "Inspirational",
        "translation": "当生活审判你时，用勇气证明自己，让行动比指控更有力。",
        "translated_word": "证明自己"
      },
      {
        "sentence": "To acquit oneself of guilt is simple; to acquit oneself of doubt requires a lifetime of reflection.",
        "style": "Philosophical",
        "translation": "洗脱罪名很简单，洗脱疑虑却需要一生的反思。",
        "translated_word": "洗脱"
      },
      {
        "sentence": "The morning sun acquits the night of its shadows, painting forgiveness across the waking sky.",
        "style": "Poetic",
        "translation": "晨曦为黑夜洗去阴影，在苏醒的天空绘上宽恕。",
        "translated_word": "洗去"
      },
      {
        "sentence": "The jury voted unanimously to acquit the defendant after new evidence proved his innocence.",
        "style": "News-like",
        "translation": "在新证据证明被告无罪后，陪审团一致投票宣判其无罪。",
        "translated_word": "宣判其无罪"
      }
    ]
  },
  {
    "word": "wilt",
    "phonetic": "/wɪlt/",
    "pos": [
      "noun",
      "verb"
    ],
    "selected_pos": "verb",
    "definition": "枯萎；凋谢；萎靡",
    "examples": [
      {
        "sentence": "Even when challenges make you wilt, remember that every flower rises again after the storm.",
        "style": "Inspirational",
        "translation": "即使挑战让你萎靡不振，请记住每朵花在风暴过后都会再次绽放。",
        "translated_word": "萎靡不振"
      },
      {
        "sentence": "Does the spirit wilt because of hardship, or does hardship reveal what was already wilting within?",
        "style": "Philosophical",
        "translation": "精神是因为苦难而枯萎，还是苦难揭示了内心早已凋零的部分？",
        "translated_word": "枯萎"
      },
      {
        "sentence": "The roses wilt beneath the autumn moon, their petals falling like whispered farewells.",
        "style": "Poetic",
        "translation": "玫瑰在秋月下凋谢，花瓣飘落如同低声的告别。",
        "translated_word": "凋谢"
      },
      {
        "sentence": "My houseplants always wilt when I forget to water them for a few days.",
        "style": "Conversational",
        "translation": "我的室内植物总是在我忘记浇水几天后就枯萎了。",
        "translated_word": "枯萎"
      }
    ]
  },
  {
    "word": "enrichment",
    "phonetic": null,
    "pos": [
      "noun"
    ],
    "selected_pos": "noun",
    "definition": "丰富；充实；富集",
    "examples": [
      {
        "sentence": "The enrichment of your mind through reading opens doors you never knew existed.",
        "style": "Inspirational",
        "translation": "通过阅读来充实你的头脑，会打开你从未想象过的大门。",
        "translated_word": "充实"
      },
      {
        "sentence": "True enrichment comes not from accumulating possessions, but from deepening our understanding of life.",
        "style": "Philosophical",
        "translation": "真正的丰富不是来自积累财富，而是来自加深我们对生命的理解。",
        "translated_word": "丰富"
      },
      {
        "sentence": "Each autumn leaf carries the enrichment of summer's golden light within its veins.",
        "style": "Poetic",
        "translation": "每片秋叶的脉络中都蕴藏着夏日金色阳光的滋养。",
        "translated_word": "滋养"
      },
      {
        "sentence": "The new community center offers programs for the cultural enrichment of local residents.",
        "style": "News-like",
        "translation": "新的社区中心为当地居民提供文化充实项目。",
        "translated_word": "充实"
      }
    ]
  },
  {
    "word": "botanical",
    "phonetic": null,
    "pos": [
      "adjective",
      "noun"
    ],
    "selected_pos": "adjective",
    "definition": "植物的；植物学的",
    "examples": [
      {
        "sentence": "Let the botanical world remind you that even the smallest seed holds the promise of magnificent growth.",
        "style": "Inspirational",
        "translation": "让植物世界提醒你，即使最小的种子也蕴含着壮丽生长的希望。",
        "translated_word": "植物"
      },
      {
        "sentence": "In botanical terms, we are all rooted in the same earth, drawing life from shared waters and sunlight.",
        "style": "Philosophical",
        "translation": "从植物学角度来说，我们都扎根于同一片土地，从共同的水源和阳光中汲取生命。",
        "translated_word": "植物学"
      },
      {
        "sentence": "The botanical garden whispered secrets of ancient ferns, their fronds dancing like emerald lace in the mist.",
        "style": "Poetic",
        "translation": "植物园低语着古老蕨类的秘密，它们的叶片如翠绿蕾丝般在薄雾中舞动。",
        "translated_word": "植物"
      },
      {
        "sentence": "The city's new botanical research center will focus on developing drought-resistant crops for arid regions.",
        "style": "News-like",
        "translation": "该市新建的植物学研究中心将致力于为干旱地区开发耐旱作物。",
        "translated_word": "植物学"
      }
    ]
  },
  {
    "word": "divinity",
    "phonetic": "/dɪˈvɪnɪti/",
    "pos": [
      "noun"
    ],
    "selected_pos": "noun",
    "definition": "神性；神灵；神学",
    "examples": [
      {
        "sentence": "There is a spark of divinity within each of us, waiting to illuminate our path to greatness.",
        "style": "Inspirational",
        "translation": "我们每个人心中都有一丝神性的火花，等待着照亮我们通往伟大的道路。",
        "translated_word": "神性"
      },
      {
        "sentence": "If divinity exists in all things, then the distinction between sacred and profane is merely an illusion.",
        "style": "Philosophical",
        "translation": "如果神性存在于万物之中，那么神圣与世俗的区别不过是一种幻觉。",
        "translated_word": "神性"
      },
      {
        "sentence": "The divinity of the sunset painted the sky in hues only heaven could conceive.",
        "style": "Poetic",
        "translation": "日落的神圣将天空染成了只有天堂才能构想的色彩。",
        "translated_word": "神圣"
      },
      {
        "sentence": "She's studying divinity at the university and hopes to become a minister someday.",
        "style": "Conversational",
        "translation": "她在大学学习神学，希望有一天能成为一名牧师。",
        "translated_word": "神学"
      }
    ]
  },
  {
    "word": "flowing",
    "phonetic": "/ˈfləʊ.ɪŋ/",
    "pos": [
      "adjective",
      "noun",
      "verb"
    ],
    "selected_pos": "adjective",
    "definition": "流动的；飘逸的；流畅的",
    "examples": [
      {
        "sentence": "Like a flowing river, your potential has no limits when you keep moving forward.",
        "style": "Inspirational",
        "translation": "如同一条流动的河流，只要你不断前行，你的潜力就没有极限。",
        "translated_word": "流动的"
      },
      {
        "sentence": "Time is a flowing current: we cannot step into the same moment twice.",
        "style": "Philosophical",
        "translation": "时间是一股流动的水流：我们无法两次踏入同一个瞬间。",
        "translated_word": "流动的"
      },
      {
        "sentence": "Her flowing hair danced with the wind like silk ribbons in a summer dream.",
        "style": "Poetic",
        "translation": "她飘逸的长发随风起舞，宛如夏日梦境中的丝带。",
        "translated_word": "飘逸的"
      },
      {
        "sentence": "I love your flowing dress; it looks so elegant and comfortable.",
        "style": "Conversational",
        "translation": "我好喜欢你这条飘逸的裙子，看起来又优雅又舒服。",
        "translated_word": "飘逸的"
      }
    ]
  },
  {
    "word": "wane",
    "phonetic": "/weɪn/",
    "pos": [
      "noun",
      "verb"
    ],
    "selected_pos": "verb",
    "definition": "减弱；衰退；消逝",
    "examples": [
      {
        "sentence": "Even when your motivation begins to wane, remember that consistency builds the foundation for greatness.",
        "style": "Inspirational",
        "translation": "即使当你的动力开始减弱时，也要记住坚持不懈是成就伟大的基石。",
        "translated_word": "减弱"
      },
      {
        "sentence": "As empires wane and new powers rise, we learn that nothing in this world is truly permanent.",
        "style": "Philosophical",
        "translation": "当帝国衰退、新势力崛起时，我们明白这世上没有什么是真正永恒的。",
        "translated_word": "衰退"
      },
      {
        "sentence": "The autumn moon will wane, yet its silver light lingers softly in the lover's waiting heart.",
        "style": "Poetic",
        "translation": "秋月终将消逝，但它银色的光芒依然轻柔地停留在恋人等待的心中。",
        "translated_word": "消逝"
      },
      {
        "sentence": "Public interest in the scandal has started to wane after weeks of constant media coverage.",
        "style": "News-like",
        "translation": "经过数周持续的媒体报道后，公众对这一丑闻的兴趣已开始减退。",
        "translated_word": "减退"
      }
    ]
  },
  {
    "word": "unfairly",
    "phonetic": null,
    "pos": [
      "adverb"
    ],
    "selected_pos": "adverb",
    "definition": "不公平地；不公正地",
    "examples": [
      {
        "sentence": "Those who were unfairly overlooked today will rise to become tomorrow's champions.",
        "style": "Inspirational",
        "translation": "那些今天被不公平地忽视的人，终将成为明天的冠军。",
        "translated_word": "不公平地"
      },
      {
        "sentence": "To judge others unfairly is to reveal the limitations of our own understanding.",
        "style": "Philosophical",
        "translation": "不公正地评判他人，恰恰暴露了我们自身认知的局限。",
        "translated_word": "不公正地"
      },
      {
        "sentence": "The autumn leaves fall unfairly: some dance in sunlight, while others rot in shadow.",
        "style": "Poetic",
        "translation": "秋叶飘落得不公平：有的在阳光下起舞，有的在阴影中腐烂。",
        "translated_word": "不公平"
      },
      {
        "sentence": "The employee claimed she was unfairly dismissed after reporting safety violations.",
        "style": "News-like",
        "translation": "该员工声称她在举报安全违规行为后遭到不公正解雇。",
        "translated_word": "不公正"
      }
    ]
  },
  {
    "word": "savage",
    "phonetic": "/ˈsævɪdʒ/",
    "pos": [
      "adjective",
      "noun",
      "verb"
    ],
    "selected_pos": "adjective",
    "definition": "凶猛的；残暴的；野蛮的",
    "examples": [
      {
        "sentence": "Channel your savage determination to overcome every obstacle standing between you and your dreams.",
        "style": "Inspirational",
        "translation": "释放你那凶猛的决心，去战胜你与梦想之间的每一个障碍。",
        "translated_word": "凶猛的"
      },
      {
        "sentence": "The line between savage instinct and civilized restraint reveals what we truly value as a species.",
        "style": "Philosophical",
        "translation": "野蛮本能与文明克制之间的界限，揭示了我们作为物种真正珍视的东西。",
        "translated_word": "野蛮"
      },
      {
        "sentence": "The winter wind howled with savage fury, stripping the last golden leaves from trembling oaks.",
        "style": "Poetic",
        "translation": "寒风以狂暴的凶猛呼啸而过，将最后的金叶从颤抖的橡树上剥落。",
        "translated_word": "凶猛"
      },
      {
        "sentence": "Critics described the comedian's savage roast of the celebrity as the highlight of the evening.",
        "style": "News-like",
        "translation": "评论人士称这位喜剧演员对名人的犀利吐槽是当晚的亮点。",
        "translated_word": "犀利"
      }
    ]
  },
  {
    "word": "forceful",
    "phonetic": "/ˈfɔɹsfəl/",
    "pos": [
      "adjective"
    ],
    "selected_pos": "adjective",
    "definition": "有力的；强有力的；坚定的",
    "examples": [
      {
        "sentence": "A forceful vision backed by relentless action can transform the impossible into reality.",
        "style": "Inspirational",
        "translation": "一个强有力的愿景加上不懈的行动，能将不可能变为现实。",
        "translated_word": "强有力的"
      },
      {
        "sentence": "The most forceful arguments are often those delivered with quiet certainty rather than loud insistence.",
        "style": "Philosophical",
        "translation": "最有力的论点往往是以平静的确信而非大声的坚持来表达的。",
        "translated_word": "有力的"
      },
      {
        "sentence": "The wind made its forceful song through the canyon, bending ancient pines like blades of grass.",
        "style": "Poetic",
        "translation": "风在峡谷中奏响它强劲的歌，将古老的松树吹弯如草叶。",
        "translated_word": "强劲的"
      },
      {
        "sentence": "The senator delivered a forceful speech calling for immediate action on climate change.",
        "style": "News-like",
        "translation": "这位参议员发表了一场有力的演讲，呼吁立即采取气候变化行动。",
        "translated_word": "有力的"
      }
    ]
  },
  {
    "word": "tack",
    "phonetic": "/tak/",
    "pos": [
      "noun",
      "verb"
    ],
    "selected_pos": "noun",
    "definition": "大头钉；策略；方向",
    "examples": [
      {
        "sentence": "Sometimes a small tack is all you need to pin your dreams to the wall and make them visible every day.",
        "style": "Inspirational",
        "translation": "有时你只需要一枚小小的大头钉，就能把梦想钉在墙上，让它每天都清晰可见。",
        "translated_word": "大头钉"
      },
      {
        "sentence": "Life offers no perfect tack; every direction we choose closes a thousand other doors.",
        "style": "Philosophical",
        "translation": "人生没有完美的方向；我们选择的每一条路都会关上无数扇其他的门。",
        "translated_word": "方向"
      },
      {
        "sentence": "Her words were a silver tack, pinning silence to the heavy curtain of the night.",
        "style": "Poetic",
        "translation": "她的话语如同一枚银色的钉子，将沉默钉在夜幕的厚重帷幔上。",
        "translated_word": "钉子"
      },
      {
        "sentence": "The company announced a new tack in its marketing strategy to attract younger consumers.",
        "style": "News-like",
        "translation": "该公司宣布在营销策略上采取新方向，以吸引更年轻的消费者。",
        "translated_word": "方向"
      }
    ]
  },
  {
    "word": "emblem",
    "phonetic": "/ˈɛmbləm/",
    "pos": [
      "noun",
      "verb"
    ],
    "selected_pos": "noun",
    "definition": "象征；徽章；标志",
    "examples": [
      {
        "sentence": "Let courage be the emblem you wear on your heart as you face each new challenge.",
        "style": "Inspirational",
        "translation": "让勇气成为你心中的徽章，伴你迎接每一个新挑战。",
        "translated_word": "徽章"
      },
      {
        "sentence": "The emblem we choose to represent ourselves reveals more about our aspirations than our achievements.",
        "style": "Philosophical",
        "translation": "我们选择代表自己的象征，更多地揭示了我们的抱负而非成就。",
        "translated_word": "象征"
      },
      {
        "sentence": "The rose stood as an emblem of love, its petals soft whispers against the morning light.",
        "style": "Poetic",
        "translation": "玫瑰是爱的象征，花瓣如晨光中的轻声细语。",
        "translated_word": "象征"
      },
      {
        "sentence": "The city unveiled its new emblem yesterday, featuring a golden phoenix rising from the waves.",
        "style": "News-like",
        "translation": "该市昨日公布了新徽章，图案为一只从波浪中升起的金色凤凰。",
        "translated_word": "徽章"
      }
    ]
  },
  {
    "word": "promised",
    "phonetic": "/ˈpɹɒm.ɪst/",
    "pos": [
      "adjective",
      "verb"
    ],
    "selected_pos": "verb",
    "definition": "承诺；许诺；保证",
    "examples": [
      {
        "sentence": "She promised herself that failure would never define her, only fuel her determination to succeed.",
        "style": "Inspirational",
        "translation": "她向自己承诺，失败永远不会定义她，只会激发她成功的决心。",
        "translated_word": "承诺"
      },
      {
        "sentence": "We often wonder whether the future we promised ourselves was ever truly ours to give.",
        "style": "Philosophical",
        "translation": "我们常常想，我们曾许诺给自己的未来，是否真的属于我们可以给予的。",
        "translated_word": "许诺"
      },
      {
        "sentence": "The dawn promised warmth, painting the sleeping hills in shades of gold and rose.",
        "style": "Poetic",
        "translation": "黎明许下温暖的诺言，用金色与玫瑰色涂抹着沉睡的山丘。",
        "translated_word": "许下"
      },
      {
        "sentence": "He promised to pick up groceries on his way home, but completely forgot about it.",
        "style": "Conversational",
        "translation": "他答应回家路上买菜，但完全忘了这事。",
        "translated_word": "答应"
      }
    ]
  },
  {
    "word": "bland",
    "phonetic": "/blænd/",
    "pos": [
      "adjective",
      "noun",
      "verb"
    ],
    "selected_pos": "adjective",
    "definition": "平淡的；乏味的；清淡的",
    "examples": [
      {
        "sentence": "A bland beginning does not dictate your story; you hold the pen to write a vibrant ending.",
        "style": "Inspirational",
        "translation": "平淡的开始并不能决定你的故事；你手握画笔，可以书写精彩的结局。",
        "translated_word": "平淡的"
      },
      {
        "sentence": "Is a bland life truly empty, or does its quietness reveal truths that noise conceals?",
        "style": "Philosophical",
        "translation": "平淡的生活真的是空虚的吗，还是它的宁静揭示了喧嚣所掩盖的真相？",
        "translated_word": "平淡的"
      },
      {
        "sentence": "The bland winter sky stretched endlessly, a canvas waiting for the first blush of spring.",
        "style": "Poetic",
        "translation": "苍白的冬日天空无尽延伸，像一幅画布等待春天的第一抹嫣红。",
        "translated_word": "苍白的"
      },
      {
        "sentence": "This soup is too bland for me; could you pass the salt?",
        "style": "Conversational",
        "translation": "这汤对我来说太清淡了，能把盐递给我吗？",
        "translated_word": "清淡"
      }
    ]
  },
  {
    "word": "gateway",
    "phonetic": "/ˈɡeɪtˌweɪ/",
    "pos": [
      "noun",
      "verb"
    ],
    "selected_pos": "noun",
    "definition": "门户；入口；通道",
    "examples": [
      {
        "sentence": "Education is the gateway to opportunities that can transform your entire life.",
        "style": "Inspirational",
        "translation": "教育是通往机遇的门户，它能够改变你的整个人生。",
        "translated_word": "门户"
      },
      {
        "sentence": "Every ending is merely a gateway to a new beginning we cannot yet perceive.",
        "style": "Philosophical",
        "translation": "每一个结束都只是通向我们尚未察觉的新开始的入口。",
        "translated_word": "入口"
      },
      {
        "sentence": "The old stone arch stood as a gateway between the forest and the whispering sea.",
        "style": "Poetic",
        "translation": "古老的石拱门矗立着，作为森林与低语大海之间的通道。",
        "translated_word": "通道"
      },
      {
        "sentence": "The new international airport will serve as a major gateway for trade and tourism in the region.",
        "style": "News-like",
        "translation": "这座新的国际机场将成为该地区贸易和旅游的重要门户。",
        "translated_word": "门户"
      }
    ]
  },
  {
    "word": "termination",
    "phonetic": "/tɚmɪˈneɪʃən/",
    "pos": [
      "noun"
    ],
    "selected_pos": "noun",
    "definition": "终止；结束；终结",
    "examples": [
      {
        "sentence": "Every termination of a bad habit marks the beginning of a better version of yourself.",
        "style": "Inspirational",
        "translation": "每一个坏习惯的终结都标志着一个更好的自己的开始。",
        "translated_word": "终结"
      },
      {
        "sentence": "The termination of one journey is merely the threshold of another; endings and beginnings are illusions of time.",
        "style": "Philosophical",
        "translation": "一段旅程的终止不过是另一段旅程的门槛；结束与开始都是时间的幻象。",
        "translated_word": "终止"
      },
      {
        "sentence": "In the termination of autumn, golden leaves write their final verses upon the sleeping earth.",
        "style": "Poetic",
        "translation": "在秋天的终结里，金黄的落叶在沉睡的大地上写下它们最后的诗篇。",
        "translated_word": "终结"
      },
      {
        "sentence": "The company announced the termination of its partnership with the supplier due to quality concerns.",
        "style": "News-like",
        "translation": "该公司宣布因质量问题终止与供应商的合作关系。",
        "translated_word": "终止"
      }
    ]
  },
  {
    "word": "stakeholder",
    "phonetic": "/ˈsteɪkhoʊldə(ɹ)/",
    "pos": [
      "noun"
    ],
    "selected_pos": "noun",
    "definition": "利益相关者；股东；参与方",
    "examples": [
      {
        "sentence": "Every stakeholder has the power to shape the future when they choose to engage with passion and purpose.",
        "style": "Inspirational",
        "translation": "每一位利益相关者都有能力塑造未来，只要他们选择以热情和目标参与其中。",
        "translated_word": "利益相关者"
      },
      {
        "sentence": "In the web of human endeavor, even the silent stakeholder bears the weight of collective consequence.",
        "style": "Philosophical",
        "translation": "在人类努力的网络中，即使是沉默的利益相关者也承担着集体后果的重量。",
        "translated_word": "利益相关者"
      },
      {
        "sentence": "Like stars bound to the same constellation, each stakeholder dances in the gravity of shared dreams.",
        "style": "Poetic",
        "translation": "如同被同一星座束缚的星辰，每位利益相关者都在共同梦想的引力中起舞。",
        "translated_word": "利益相关者"
      },
      {
        "sentence": "The company held a meeting with key stakeholders to discuss the proposed merger.",
        "style": "News-like",
        "translation": "该公司与主要利益相关方举行会议，讨论拟议中的合并事宜。",
        "translated_word": "利益相关方"
      }
    ]
  },
  {
    "word": "hegemony",
    "phonetic": "/hɪˈdʒɛm.ə.ni/",
    "pos": [
      "noun"
    ],
    "selected_pos": "noun",
    "definition": "霸权；主导权；支配地位",
    "examples": [
      {
        "sentence": "True leadership is not about hegemony, but about lifting others to stand beside you.",
        "style": "Inspirational",
        "translation": "真正的领导力不在于霸权，而在于提升他人，使其与你并肩而立。",
        "translated_word": "霸权"
      },
      {
        "sentence": "Every hegemony carries within it the seeds of its own dissolution.",
        "style": "Philosophical",
        "translation": "每一种霸权都在自身内部孕育着瓦解的种子。",
        "translated_word": "霸权"
      },
      {
        "sentence": "The empire's hegemony stretched like a shadow across silent lands, cold and absolute.",
        "style": "Poetic",
        "translation": "帝国的霸权如阴影般笼罩着沉默的大地，冰冷而绝对。",
        "translated_word": "霸权"
      },
      {
        "sentence": "Analysts warn that the shifting global order may challenge traditional hegemony in trade and technology.",
        "style": "News-like",
        "translation": "分析人士警告，不断变化的全球秩序可能会挑战贸易和技术领域的传统霸权。",
        "translated_word": "霸权"
      }
    ]
  },
  {
    "word": "homage",
    "phonetic": "/ˈhɒmɪdʒ/",
    "pos": [
      "noun",
      "verb"
    ],
    "selected_pos": "noun",
    "definition": "敬意；致敬；崇敬",
    "examples": [
      {
        "sentence": "Every small act of kindness we perform is a homage to the better world we wish to create.",
        "style": "Inspirational",
        "translation": "我们所做的每一件小善事，都是对我们期望创造的美好世界的致敬。",
        "translated_word": "致敬"
      },
      {
        "sentence": "To live authentically is the deepest homage one can pay to the gift of existence.",
        "style": "Philosophical",
        "translation": "真实地活着，是一个人对生命馈赠所能表达的最深敬意。",
        "translated_word": "敬意"
      },
      {
        "sentence": "The autumn leaves fall in silent homage to the trees that held them through summer's warmth.",
        "style": "Poetic",
        "translation": "秋叶无声飘落，向那些在夏日温暖中承托它们的树木致以崇敬。",
        "translated_word": "崇敬"
      },
      {
        "sentence": "The museum unveiled a new exhibit paying homage to the pioneers of modern art.",
        "style": "News-like",
        "translation": "博物馆揭幕了一场向现代艺术先驱致敬的新展览。",
        "translated_word": "致敬"
      }
    ]
  },
  {
    "word": "fed",
    "phonetic": "/fɛd/",
    "pos": [
      "noun",
      "verb"
    ],
    "selected_pos": "verb",
    "definition": "喂养；供给；输入",
    "examples": [
      {
        "sentence": "She fed her dreams with hard work and perseverance until they became reality.",
        "style": "Inspirational",
        "translation": "她用努力和坚持喂养自己的梦想，直到梦想成真。",
        "translated_word": "喂养"
      },
      {
        "sentence": "We fed the fire of progress, never asking what the flames would consume.",
        "style": "Philosophical",
        "translation": "我们供给进步之火燃料，却从不问火焰会吞噬什么。",
        "translated_word": "供给"
      },
      {
        "sentence": "The river fed the valley with whispers of ancient rain.",
        "style": "Poetic",
        "translation": "河流用远古雨水的低语滋养着山谷。",
        "translated_word": "滋养"
      },
      {
        "sentence": "The charity fed over two thousand families during the holiday season.",
        "style": "News-like",
        "translation": "该慈善机构在节日期间为两千多个家庭提供了食物。",
        "translated_word": "提供了食物"
      }
    ]
  },
  {
    "word": "displaced",
    "phonetic": null,
    "pos": [
      "verb"
    ],
    "selected_pos": "verb",
    "definition": "取代；迫使离开；使流离失所",
    "examples": [
      {
        "sentence": "When fear displaced hope in her heart, she chose to fight back and reclaim her dreams.",
        "style": "Inspirational",
        "translation": "当恐惧取代了她心中的希望时，她选择奋起反击，重新追寻梦想。",
        "translated_word": "取代"
      },
      {
        "sentence": "Every truth we embrace has displaced an illusion we once held dear.",
        "style": "Philosophical",
        "translation": "我们所接受的每一个真理，都取代了曾经珍视的幻象。",
        "translated_word": "取代"
      },
      {
        "sentence": "The rising tide displaced the silence of the shore with its ancient, whispering song.",
        "style": "Poetic",
        "translation": "涨潮的海水用亘古的低语之歌，取代了海岸的寂静。",
        "translated_word": "取代"
      },
      {
        "sentence": "The flooding displaced thousands of residents who are now seeking temporary shelter.",
        "style": "News-like",
        "translation": "洪水迫使数千居民流离失所，他们正在寻找临时住所。",
        "translated_word": "流离失所"
      }
    ]
  },
  {
    "word": "thriving",
    "phonetic": "/θɹaɪvɪŋ/",
    "pos": [
      "adjective",
      "noun",
      "verb"
    ],
    "selected_pos": "adjective",
    "definition": "繁荣的；兴旺的；蓬勃发展的",
    "examples": [
      {
        "sentence": "A thriving mind is one that embraces challenges as opportunities for growth.",
        "style": "Inspirational",
        "translation": "一个蓬勃发展的头脑会把挑战视为成长的机会。",
        "translated_word": "蓬勃发展的"
      },
      {
        "sentence": "Can a society be truly thriving if its people have lost the capacity for wonder?",
        "style": "Philosophical",
        "translation": "如果人们失去了惊叹的能力，这个社会还能算真正繁荣吗？",
        "translated_word": "繁荣"
      },
      {
        "sentence": "In the garden of dawn, thriving roses whisper secrets to the morning sun.",
        "style": "Poetic",
        "translation": "在黎明的花园里，盛开的玫瑰向朝阳低语秘密。",
        "translated_word": "盛开的"
      },
      {
        "sentence": "The city's thriving tech sector has attracted investors from around the world.",
        "style": "News-like",
        "translation": "该市蓬勃发展的科技行业吸引了来自世界各地的投资者。",
        "translated_word": "蓬勃发展的"
      }
    ]
  },
  {
    "word": "mobilization",
    "phonetic": null,
    "pos": [
      "noun"
    ],
    "selected_pos": "noun",
    "definition": "动员；调动；集结",
    "examples": [
      {
        "sentence": "The mobilization of an entire community can turn impossible dreams into shared victories.",
        "style": "Inspirational",
        "translation": "整个社区的动员可以将不可能的梦想变成共同的胜利。",
        "translated_word": "动员"
      },
      {
        "sentence": "True mobilization begins not with resources, but with the awakening of collective purpose.",
        "style": "Philosophical",
        "translation": "真正的动员不是从资源开始，而是从集体目标的觉醒开始。",
        "translated_word": "动员"
      },
      {
        "sentence": "Like rivers gathering into one great sea, the mobilization of hearts creates unstoppable tides.",
        "style": "Poetic",
        "translation": "如同河流汇聚成汪洋大海，人心的集结创造出势不可挡的浪潮。",
        "translated_word": "集结"
      },
      {
        "sentence": "The government announced a nationwide mobilization of healthcare workers to combat the outbreak.",
        "style": "News-like",
        "translation": "政府宣布在全国范围内调动医护人员以应对疫情。",
        "translated_word": "调动"
      }
    ]
  },
  {
    "word": "clipping",
    "phonetic": "/ˈklɪpɪŋ/",
    "pos": [
      "noun",
      "verb"
    ],
    "selected_pos": "noun",
    "definition": "剪报；剪辑片段；修剪物",
    "examples": [
      {
        "sentence": "She kept a clipping of her first published article as a reminder that dreams do come true.",
        "style": "Inspirational",
        "translation": "她保留着自己第一篇发表文章的剪报，提醒自己梦想确实会成真。",
        "translated_word": "剪报"
      },
      {
        "sentence": "A newspaper clipping from decades ago can reveal how differently we once understood the world.",
        "style": "Philosophical",
        "translation": "一张几十年前的报纸剪报能揭示我们曾经对世界的理解是多么不同。",
        "translated_word": "剪报"
      },
      {
        "sentence": "The faded clipping lay pressed between pages, a brittle whisper of time preserved in ink.",
        "style": "Poetic",
        "translation": "那张褪色的剪报夹在书页间，是用墨水保存的时光的脆弱低语。",
        "translated_word": "剪报"
      },
      {
        "sentence": "I found an old clipping about grandma's bakery while cleaning out the attic yesterday.",
        "style": "Conversational",
        "translation": "昨天清理阁楼时，我发现了一张关于奶奶面包店的旧剪报。",
        "translated_word": "剪报"
      }
    ]
  },
  {
    "word": "convergence",
    "phonetic": "/kɒnˈvɜː(ɹ)d͡ʒəns/",
    "pos": [
      "noun"
    ],
    "selected_pos": "noun",
    "definition": "汇聚；交汇；融合",
    "examples": [
      {
        "sentence": "The convergence of your skills and passions is where you'll find your true calling.",
        "style": "Inspirational",
        "translation": "你的技能与热情的交汇之处，正是你发现真正使命的地方。",
        "translated_word": "交汇"
      },
      {
        "sentence": "Every great discovery emerges from the convergence of curiosity and persistence.",
        "style": "Philosophical",
        "translation": "每一个伟大的发现都源于好奇心与坚持的融合。",
        "translated_word": "融合"
      },
      {
        "sentence": "At the convergence of river and sea, the waters dance in shades of blue and green.",
        "style": "Poetic",
        "translation": "在河流与大海的汇聚处，水波舞动着蓝与绿的色彩。",
        "translated_word": "汇聚"
      },
      {
        "sentence": "The convergence of global leaders at the summit signals renewed efforts toward climate action.",
        "style": "News-like",
        "translation": "全球领导人在峰会上的汇聚标志着应对气候变化的新努力。",
        "translated_word": "汇聚"
      }
    ]
  },
  {
    "word": "immensely",
    "phonetic": "/ɪˈmɛnsli/",
    "pos": [
      "adverb"
    ],
    "selected_pos": "adverb",
    "definition": "极其；非常；极大地",
    "examples": [
      {
        "sentence": "Believing in yourself immensely expands the boundaries of what you can achieve.",
        "style": "Inspirational",
        "translation": "相信自己会极大地拓展你所能达到的边界。",
        "translated_word": "极大地"
      },
      {
        "sentence": "We are immensely small in the universe, yet our capacity to wonder makes us infinitely significant.",
        "style": "Philosophical",
        "translation": "我们在宇宙中极其渺小，但我们惊叹万物的能力使我们无限重要。",
        "translated_word": "极其"
      },
      {
        "sentence": "The moon hung low, immensely bright, spilling silver across the sleeping sea.",
        "style": "Poetic",
        "translation": "月亮低悬，异常明亮，将银辉洒满沉睡的大海。",
        "translated_word": "异常"
      },
      {
        "sentence": "I enjoyed the trip immensely; the food and the people were just wonderful.",
        "style": "Conversational",
        "translation": "我非常享受这次旅行，美食和人们都太棒了。",
        "translated_word": "非常"
      }
    ]
  },
  {
    "word": "imagined",
    "phonetic": "/ɪˈmædʒɪnd/",
    "pos": [
      "adjective",
      "verb"
    ],
    "selected_pos": "verb",
    "definition": "想象；设想；幻想",
    "examples": [
      {
        "sentence": "She imagined a future where her dreams became reality, and that vision gave her the courage to begin.",
        "style": "Inspirational",
        "translation": "她想象着一个梦想成真的未来，这个愿景给了她开始的勇气。",
        "translated_word": "想象"
      },
      {
        "sentence": "We often discover that what we imagined to be impossible was merely untested.",
        "style": "Philosophical",
        "translation": "我们常常发现，那些我们以为不可能的事，只是未曾尝试过而已。",
        "translated_word": "以为"
      },
      {
        "sentence": "He imagined her voice in the wind, a gentle echo that lingered like morning mist.",
        "style": "Poetic",
        "translation": "他在风中幻想着她的声音，那温柔的回响如晨雾般萦绕不散。",
        "translated_word": "幻想"
      },
      {
        "sentence": "I never imagined we'd run into each other at a tiny coffee shop in Paris.",
        "style": "Conversational",
        "translation": "我从没想到我们会在巴黎一家小咖啡馆里偶遇。",
        "translated_word": "想到"
      }
    ]
  },
  {
    "word": "palpable",
    "phonetic": "/ˈpalpəbəl/",
    "pos": [
      "adjective"
    ],
    "selected_pos": "adjective",
    "definition": "明显的；可触知的；可感知的",
    "examples": [
      {
        "sentence": "The excitement in the room was palpable as she stepped onto the stage to accept her award.",
        "style": "Inspirational",
        "translation": "当她走上舞台领奖时，房间里的兴奋之情显而易见。",
        "translated_word": "显而易见"
      },
      {
        "sentence": "Is truth palpable, or does it only exist in the spaces between what we can prove?",
        "style": "Philosophical",
        "translation": "真理是可感知的，还是只存在于我们能证明之事的间隙之中？",
        "translated_word": "可感知的"
      },
      {
        "sentence": "The silence between them grew palpable, heavy as fog rolling over still water.",
        "style": "Poetic",
        "translation": "他们之间的沉默变得触手可及，沉重得如同浓雾笼罩着静水。",
        "translated_word": "触手可及"
      },
      {
        "sentence": "Tension was palpable at the summit as leaders gathered to discuss the ongoing crisis.",
        "style": "News-like",
        "translation": "领导人齐聚讨论持续危机时，峰会上的紧张气氛显而易见。",
        "translated_word": "显而易见"
      }
    ]
  },
  {
    "word": "aboriginal",
    "phonetic": "/ˌæb.əˈɹɪd͡ʒ.n̩.l̩/",
    "pos": [
      "adjective",
      "noun"
    ],
    "selected_pos": "adjective",
    "definition": "土著的；原始的；原住民的",
    "examples": [
      {
        "sentence": "Aboriginal wisdom teaches us that caring for the land is caring for ourselves and future generations.",
        "style": "Inspirational",
        "translation": "土著智慧教导我们，守护土地就是守护我们自己和子孙后代。",
        "translated_word": "土著"
      },
      {
        "sentence": "Aboriginal cultures remind us that progress without roots is merely motion without meaning.",
        "style": "Philosophical",
        "translation": "原住民文化提醒我们，没有根基的进步只是毫无意义的移动。",
        "translated_word": "原住民"
      },
      {
        "sentence": "Under ancient stars, aboriginal songs drift across the desert like whispers of the dreaming earth.",
        "style": "Poetic",
        "translation": "在古老的星空下，土著歌谣飘过沙漠，如同大地梦境的低语。",
        "translated_word": "土著"
      },
      {
        "sentence": "The museum unveiled a new exhibit featuring aboriginal art from Australia's Northern Territory.",
        "style": "News-like",
        "translation": "博物馆揭幕了一个新展览，展出来自澳大利亚北领地的原住民艺术作品。",
        "translated_word": "原住民"
      }
    ]
  },
  {
    "word": "whim",
    "phonetic": "/wɪm/",
    "pos": [
      "noun",
      "verb"
    ],
    "selected_pos": "noun",
    "definition": "一时兴起；突发奇想；心血来潮",
    "examples": [
      {
        "sentence": "Follow your whim today; sometimes the unplanned path leads to the greatest adventures.",
        "style": "Inspirational",
        "translation": "今天就跟随你的一时兴起吧；有时候未经计划的道路会通向最伟大的冒险。",
        "translated_word": "一时兴起"
      },
      {
        "sentence": "Is free will merely a whim dressed in the illusion of purpose?",
        "style": "Philosophical",
        "translation": "自由意志是否只是披着目的外衣的心血来潮？",
        "translated_word": "心血来潮"
      },
      {
        "sentence": "The wind obeys no master, dancing on the whim of seasons.",
        "style": "Poetic",
        "translation": "风不听从任何主人，随着季节的突发奇想翩翩起舞。",
        "translated_word": "突发奇想"
      },
      {
        "sentence": "I bought this vintage camera on a whim at the flea market last weekend.",
        "style": "Conversational",
        "translation": "上周末我在跳蚤市场一时兴起买了这台复古相机。",
        "translated_word": "一时兴起"
      }
    ]
  },
  {
    "word": "spotted",
    "phonetic": "/ˈspɒtɨd/",
    "pos": [
      "adjective",
      "verb"
    ],
    "selected_pos": "verb",
    "definition": "发现；注意到；认出",
    "examples": [
      {
        "sentence": "She spotted her own potential when everyone else overlooked it, and that discovery changed her life forever.",
        "style": "Inspirational",
        "translation": "当所有人都忽视她时，她发现了自己的潜力，这个发现永远改变了她的人生。",
        "translated_word": "发现"
      },
      {
        "sentence": "We spend our lives searching for meaning, yet rarely have we spotted the truth hiding in plain sight.",
        "style": "Philosophical",
        "translation": "我们穷尽一生寻找意义，却很少注意到那显而易见的真相。",
        "translated_word": "注意到"
      },
      {
        "sentence": "Through morning mist, the sailor spotted a lone seabird dancing on the silver waves.",
        "style": "Poetic",
        "translation": "透过晨雾，水手望见一只孤鸟在银色波浪上翩翩起舞。",
        "translated_word": "望见"
      },
      {
        "sentence": "I spotted my old college roommate at the coffee shop yesterday; what a small world!",
        "style": "Conversational",
        "translation": "我昨天在咖啡店认出了我大学室友，世界真小！",
        "translated_word": "认出"
      }
    ]
  },
  {
    "word": "watchdog",
    "phonetic": null,
    "pos": [
      "noun",
      "verb"
    ],
    "selected_pos": "noun",
    "definition": "监督者；看门狗",
    "examples": [
      {
        "sentence": "Be the watchdog of your own dreams; guard them fiercely against doubt and distraction.",
        "style": "Inspirational",
        "translation": "做自己梦想的守护者；坚定地守护它们，抵御怀疑和干扰。",
        "translated_word": "守护者"
      },
      {
        "sentence": "Society needs a watchdog not to punish the wicked, but to remind the powerful of their accountability.",
        "style": "Philosophical",
        "translation": "社会需要监督者，不是为了惩罚恶人，而是为了提醒当权者他们的责任。",
        "translated_word": "监督者"
      },
      {
        "sentence": "The moon stands as a silent watchdog over sleeping cities, bathing rooftops in silver light.",
        "style": "Poetic",
        "translation": "月亮如同一位沉默的守望者，俯瞰沉睡的城市，将银色的光芒洒满屋顶。",
        "translated_word": "守望者"
      },
      {
        "sentence": "The consumer watchdog has launched an investigation into the company's misleading advertising practices.",
        "style": "News-like",
        "translation": "消费者监督机构已对该公司的虚假广告行为展开调查。",
        "translated_word": "监督机构"
      }
    ]
  },
  {
    "word": "pickle",
    "phonetic": "/ˈpɪkl̩/",
    "pos": [
      "noun",
      "verb"
    ],
    "selected_pos": "noun",
    "definition": "腌黄瓜；困境",
    "examples": [
      {
        "sentence": "Every pickle you find yourself in is just an opportunity to discover strengths you never knew you had.",
        "style": "Inspirational",
        "translation": "你所陷入的每一个困境，都是发现自己未知力量的机会。",
        "translated_word": "困境"
      },
      {
        "sentence": "Life's greatest lessons often come wrapped in a pickle, teaching us that discomfort precedes growth.",
        "style": "Philosophical",
        "translation": "人生最宝贵的教训往往隐藏在困境之中，教会我们成长总是伴随着不适。",
        "translated_word": "困境"
      },
      {
        "sentence": "She stood in a pickle of her own making, like a bird tangled in threads of morning mist.",
        "style": "Poetic",
        "translation": "她陷入了自己造成的困境，如同一只困在晨雾丝缕中的鸟儿。",
        "translated_word": "困境"
      },
      {
        "sentence": "I'm in a real pickle here; I promised to help both of them move on the same day.",
        "style": "Conversational",
        "translation": "我现在真是进退两难；我答应了同一天帮他们两个搬家。",
        "translated_word": "进退两难"
      }
    ]
  },
  {
    "word": "stationary",
    "phonetic": "/ˈsteɪʃ(ə)n(ə)ɹi/",
    "pos": [
      "adjective",
      "noun"
    ],
    "selected_pos": "adjective",
    "definition": "静止的；固定的；不动的",
    "examples": [
      {
        "sentence": "Never stay stationary in life; growth comes from the courage to keep moving forward.",
        "style": "Inspirational",
        "translation": "生活中永远不要停滞不前；成长源于不断前进的勇气。",
        "translated_word": "停滞不前"
      },
      {
        "sentence": "Is anything truly stationary, or is stillness merely motion too slow for our eyes to perceive?",
        "style": "Philosophical",
        "translation": "有什么是真正静止的吗，还是静止只是我们眼睛无法察觉的缓慢运动？",
        "translated_word": "静止"
      },
      {
        "sentence": "The heron stood stationary by the lake, a silver sculpture beneath the pale morning moon.",
        "style": "Poetic",
        "translation": "苍鹭静立于湖畔，宛如淡月晨光下的一尊银色雕塑。",
        "translated_word": "静立"
      },
      {
        "sentence": "The car remained stationary at the intersection because the traffic light was broken.",
        "style": "Conversational",
        "translation": "那辆车停在路口一动不动，因为交通灯坏了。",
        "translated_word": "一动不动"
      }
    ]
  },
  {
    "word": "continual",
    "phonetic": "/kənˈtɪnjuəl/",
    "pos": [
      "adjective"
    ],
    "selected_pos": "adjective",
    "definition": "持续的；不断的；反复的",
    "examples": [
      {
        "sentence": "Continual effort, not strength or intelligence, is the key to unlocking our true potential.",
        "style": "Inspirational",
        "translation": "持续的努力，而非力量或智慧，才是释放我们真正潜能的关键。",
        "translated_word": "持续的"
      },
      {
        "sentence": "Is identity a fixed state, or merely the continual process of becoming who we are?",
        "style": "Philosophical",
        "translation": "身份是一种固定状态，还是仅仅是我们不断成为自己的过程？",
        "translated_word": "不断"
      },
      {
        "sentence": "Like the continual turning of seasons, love fades and blooms again in silent rhythm.",
        "style": "Poetic",
        "translation": "如同四季的不断更迭，爱在无声的韵律中消逝又重新绽放。",
        "translated_word": "不断"
      },
      {
        "sentence": "The continual interruptions during the meeting made it impossible to finish on time.",
        "style": "Conversational",
        "translation": "会议期间不断的打扰让我们根本无法按时结束。",
        "translated_word": "不断的"
      }
    ]
  },
  {
    "word": "ridicule",
    "phonetic": "/ˈɹɪdɪkjuːl/",
    "pos": [
      "adjective",
      "noun",
      "verb"
    ],
    "selected_pos": "noun",
    "definition": "嘲笑；讥讽；奚落",
    "examples": [
      {
        "sentence": "The ridicule she faced only strengthened her resolve to prove everyone wrong.",
        "style": "Inspirational",
        "translation": "她所遭受的嘲笑只会让她更加坚定地证明所有人都错了。",
        "translated_word": "嘲笑"
      },
      {
        "sentence": "Ridicule reveals more about the mocker than the mocked; it is fear dressed as superiority.",
        "style": "Philosophical",
        "translation": "嘲讽更多地暴露了嘲笑者而非被嘲笑者；它是披着优越感外衣的恐惧。",
        "translated_word": "嘲讽"
      },
      {
        "sentence": "Her dreams became a garden where the weeds of ridicule could never take root.",
        "style": "Poetic",
        "translation": "她的梦想化作一座花园，讥笑的杂草永远无法在此扎根。",
        "translated_word": "讥笑"
      },
      {
        "sentence": "The proposal was met with ridicule from senior officials during the meeting.",
        "style": "News-like",
        "translation": "该提案在会议上遭到了高级官员的奚落。",
        "translated_word": "奚落"
      }
    ]
  },
  {
    "word": "virgin",
    "phonetic": "/ˈvɜːdʒɪn/",
    "pos": [
      "adjective",
      "noun"
    ],
    "selected_pos": "adjective",
    "definition": "未开发的；原始的；首次的",
    "examples": [
      {
        "sentence": "Every virgin attempt at something new is a chance to discover strengths you never knew you had.",
        "style": "Inspirational",
        "translation": "每一次全新的首次尝试，都是发现自己未知力量的机会。",
        "translated_word": "首次"
      },
      {
        "sentence": "The virgin mind, untouched by assumption, often sees truths that experience has learned to overlook.",
        "style": "Philosophical",
        "translation": "未经世事的纯净心灵，往往能看到经验已学会忽视的真相。",
        "translated_word": "纯净"
      },
      {
        "sentence": "She wandered through the virgin forest, where ancient trees whispered secrets no human had ever heard.",
        "style": "Poetic",
        "translation": "她漫步于原始森林中，古老的树木低语着从未有人听过的秘密。",
        "translated_word": "原始"
      },
      {
        "sentence": "Scientists discovered a virgin ecosystem deep in the cave, completely untouched by human activity.",
        "style": "News-like",
        "translation": "科学家在洞穴深处发现了一个未开发的生态系统，完全未受人类活动影响。",
        "translated_word": "未开发的"
      }
    ]
  },
  {
    "word": "pitching",
    "phonetic": "/ˈpɪtʃtɪŋ/",
    "pos": [
      "noun",
      "verb"
    ],
    "selected_pos": "verb",
    "definition": "推销；投球；搭建",
    "examples": [
      {
        "sentence": "Keep pitching your dreams to the world; someone out there is ready to believe in your vision.",
        "style": "Inspirational",
        "translation": "继续向世界推销你的梦想；总有人会相信你的愿景。",
        "translated_word": "推销"
      },
      {
        "sentence": "Life is constantly pitching us challenges, and our character is revealed by how we swing back.",
        "style": "Philosophical",
        "translation": "生活不断向我们抛出挑战，而我们的品格在于如何回击。",
        "translated_word": "抛出"
      },
      {
        "sentence": "The autumn wind was pitching golden leaves across the silent lake like scattered whispers.",
        "style": "Poetic",
        "translation": "秋风将金黄的落叶抛向寂静的湖面，如同散落的低语。",
        "translated_word": "抛"
      },
      {
        "sentence": "She spent the whole afternoon pitching her startup idea to potential investors at the conference.",
        "style": "Conversational",
        "translation": "她整个下午都在会议上向潜在投资者推销她的创业想法。",
        "translated_word": "推销"
      }
    ]
  },
  {
    "word": "angular",
    "phonetic": "/-lɑɹ/",
    "pos": [
      "adjective",
      "noun"
    ],
    "selected_pos": "adjective",
    "definition": "棱角分明的；瘦削的；生硬的",
    "examples": [
      {
        "sentence": "Her angular features reflected years of discipline and determination, a face sculpted by relentless pursuit of excellence.",
        "style": "Inspirational",
        "translation": "她棱角分明的面容映射出多年的自律与决心，那是一张被不懈追求卓越所雕琢的脸。",
        "translated_word": "棱角分明的"
      },
      {
        "sentence": "We smooth our angular edges to fit in, yet lose ourselves in the process of becoming round.",
        "style": "Philosophical",
        "translation": "我们磨平自己生硬的棱角以融入群体，却在变得圆滑的过程中迷失了自我。",
        "translated_word": "生硬的"
      },
      {
        "sentence": "The angular branches of winter oaks reach toward the sky like the hands of old poets grasping at fading stars.",
        "style": "Poetic",
        "translation": "冬日橡树瘦削的枝条伸向天空，如同老诗人的手，试图抓住渐逝的星辰。",
        "translated_word": "瘦削的"
      },
      {
        "sentence": "The architect's angular design divided critics, with some praising its boldness while others found it too stark.",
        "style": "News-like",
        "translation": "这位建筑师棱角分明的设计引发了评论界的分歧，有人赞赏其大胆，也有人觉得过于生硬。",
        "translated_word": "棱角分明的"
      }
    ]
  },
  {
    "word": "imperfect",
    "phonetic": null,
    "pos": [
      "adjective",
      "noun",
      "verb"
    ],
    "selected_pos": "adjective",
    "definition": "不完美的；有缺陷的；有瑕疵的",
    "examples": [
      {
        "sentence": "Your imperfect attempts today are building the foundation for your perfect achievements tomorrow.",
        "style": "Inspirational",
        "translation": "你今天不完美的尝试，正在为明天完美的成就奠定基础。",
        "translated_word": "不完美的"
      },
      {
        "sentence": "In an imperfect world, the pursuit of perfection itself becomes a beautiful contradiction.",
        "style": "Philosophical",
        "translation": "在一个不完美的世界里，追求完美本身就成了一种美丽的矛盾。",
        "translated_word": "不完美的"
      },
      {
        "sentence": "She loved him not despite his imperfect heart, but because of the cracks that let light through.",
        "style": "Poetic",
        "translation": "她爱他，不是尽管他有一颗不完美的心，而是因为那些裂缝让光透了进来。",
        "translated_word": "不完美的"
      },
      {
        "sentence": "I know my English is imperfect, but at least I can order coffee without pointing at the menu.",
        "style": "Conversational",
        "translation": "我知道我的英语不完美，但至少我能点咖啡而不用指着菜单。",
        "translated_word": "不完美"
      }
    ]
  },
  {
    "word": "revert",
    "phonetic": "/ɹɨˈvɜːt/",
    "pos": [
      "noun",
      "verb"
    ],
    "selected_pos": "verb",
    "definition": "恢复；回复；回归",
    "examples": [
      {
        "sentence": "When life knocks you down, don't revert to old fears; instead, rise with newfound courage.",
        "style": "Inspirational",
        "translation": "当生活把你击倒时，不要回归旧日的恐惧；相反，要带着新生的勇气站起来。",
        "translated_word": "回归"
      },
      {
        "sentence": "We often revert to familiar patterns, questioning whether change is growth or mere illusion.",
        "style": "Philosophical",
        "translation": "我们常常回复到熟悉的模式，质疑改变究竟是成长还是仅仅是幻觉。",
        "translated_word": "回复"
      },
      {
        "sentence": "Like autumn leaves returning to earth, we revert to silence when words can no longer hold our hearts.",
        "style": "Poetic",
        "translation": "如同秋叶归于大地，当言语无法再承载我们的心时，我们回归沉默。",
        "translated_word": "回归"
      },
      {
        "sentence": "The city council voted to revert the park to its original design after public outcry.",
        "style": "News-like",
        "translation": "在公众强烈抗议后，市议会投票决定将公园恢复到原来的设计。",
        "translated_word": "恢复"
      }
    ]
  },
  {
    "word": "periphery",
    "phonetic": "/pəˈɹɪfəɹi/",
    "pos": [
      "noun"
    ],
    "selected_pos": "noun",
    "definition": "边缘；外围；边界",
    "examples": [
      {
        "sentence": "Great achievements often begin at the periphery of your comfort zone, where growth awaits.",
        "style": "Inspirational",
        "translation": "伟大的成就往往始于舒适区的边缘，那里有成长在等待着你。",
        "translated_word": "边缘"
      },
      {
        "sentence": "What we dismiss to the periphery of our attention may hold the truths we seek.",
        "style": "Philosophical",
        "translation": "我们忽略到注意力外围的事物，可能正藏着我们寻找的真理。",
        "translated_word": "外围"
      },
      {
        "sentence": "Stars scattered along the periphery of night, whispering secrets to the sleeping earth.",
        "style": "Poetic",
        "translation": "星星散落在夜的边缘，向沉睡的大地低语着秘密。",
        "translated_word": "边缘"
      },
      {
        "sentence": "The new housing development on the city's periphery has attracted thousands of young families.",
        "style": "News-like",
        "translation": "城市外围的新住宅开发项目已吸引了数千个年轻家庭。",
        "translated_word": "外围"
      }
    ]
  },
  {
    "word": "patronage",
    "phonetic": "/ˈpeɪtɹənɪd͡ʒ/",
    "pos": [
      "noun",
      "verb"
    ],
    "selected_pos": "noun",
    "definition": "赞助；光顾；恩惠",
    "examples": [
      {
        "sentence": "Your patronage of local artists today plants the seeds of tomorrow's masterpieces.",
        "style": "Inspirational",
        "translation": "你今天对本地艺术家的赞助，播下了明日杰作的种子。",
        "translated_word": "赞助"
      },
      {
        "sentence": "True patronage lies not in the giving of wealth, but in the recognition of worth.",
        "style": "Philosophical",
        "translation": "真正的赞助不在于给予财富，而在于认可价值。",
        "translated_word": "赞助"
      },
      {
        "sentence": "Under the quiet patronage of moonlight, the garden whispered its ancient secrets.",
        "style": "Poetic",
        "translation": "在月光静谧的庇护下，花园低语着它古老的秘密。",
        "translated_word": "庇护"
      },
      {
        "sentence": "The museum announced that corporate patronage had doubled over the past fiscal year.",
        "style": "News-like",
        "translation": "博物馆宣布，企业赞助在过去一个财年中翻了一番。",
        "translated_word": "赞助"
      }
    ]
  },
  {
    "word": "engaging",
    "phonetic": "/ɪnˈɡeɪd͡ʒɪŋ/",
    "pos": [
      "adjective",
      "verb"
    ],
    "selected_pos": "adjective",
    "definition": "吸引人的；迷人的；有魅力的",
    "examples": [
      {
        "sentence": "An engaging personality can open doors that talent alone cannot.",
        "style": "Inspirational",
        "translation": "迷人的个性能打开仅凭才华无法开启的大门。",
        "translated_word": "迷人的"
      },
      {
        "sentence": "We find certain ideas engaging not because they are true, but because they challenge what we believe.",
        "style": "Philosophical",
        "translation": "我们觉得某些想法引人入胜，并非因为它们是真理，而是因为它们挑战了我们的信念。",
        "translated_word": "引人入胜"
      },
      {
        "sentence": "Her voice was like an engaging melody, weaving through the silence of the night.",
        "style": "Poetic",
        "translation": "她的声音如同一曲动人的旋律，穿梭于夜的寂静之中。",
        "translated_word": "动人的"
      },
      {
        "sentence": "The professor's engaging lecture style kept students attentive for the entire two hours.",
        "style": "News-like",
        "translation": "这位教授富有吸引力的授课风格让学生们全程专注了整整两个小时。",
        "translated_word": "富有吸引力的"
      }
    ]
  }
]