{
  "word": "pessimism",
  "phonetic": "/ˈpesɪmɪzəm/",
  "pos": [
    "noun"
  ],
  "selected_pos": "noun",
  "definition": "悲观；悲观主义；消极态度",
  "examples": [
    {
      "sentence": "After three failed startups, his pessimism felt earned.",
      "style": "Contextual",
      "translation": "三次创业失败后，他的悲观显得情有可原。",
      "translated_word": "悲观",
      "display_order": 1
    },
    {
      "sentence": "Skepticism questions; pessimism surrenders.",
      "style": "Contrastive",
      "translation": "怀疑是追问，悲观是放弃。",
      "translated_word": "悲观",
      "display_order": 4
    },
    {
      "sentence": "Pessimism is the refuge of those who fear being disappointed twice.",
      "style": "Philosophical",
      "translation": "悲观是害怕再次失望之人的避难所。",
      "translated_word": "悲观",
      "display_order": 3
    },
    {
      "sentence": "She wore her pessimism lightly, like a coat she never quite took off.",
      "style": "Intimate",
      "translation": "她轻轻披着悲观，像一件始终未曾脱下的外套。",
      "translated_word": "悲观",
      "display_order": 2
    }
  ]
}