{
  "word": "monster",
  "phonetic": "/ˈmɒnstə(ɹ)/",
  "pos": [
    "adjective",
    "noun",
    "verb"
  ],
  "selected_pos": "noun",
  "definition": "怪物；巨兽；恶魔",
  "examples": [
    {
      "sentence": "The child swore a monster lived under his bed.",
      "style": "Contextual",
      "translation": "那孩子坚信床底下住着一只怪物。",
      "translated_word": "怪物",
      "display_order": 4
    },
    {
      "sentence": "We create the monsters we fear most.",
      "style": "Philosophical",
      "translation": "我们亲手创造了自己最恐惧的怪物。",
      "translated_word": "怪物",
      "display_order": 2
    },
    {
      "sentence": "Every shadow holds a monster until the light arrives.",
      "style": "Poetic",
      "translation": "每一道阴影里都藏着怪物，直到光明降临。",
      "translated_word": "怪物",
      "display_order": 3
    },
    {
      "sentence": "I once feared the monster in the mirror; now I call her my strength.",
      "style": "Intimate",
      "translation": "我曾惧怕镜中的怪物，如今我称她为我的力量。",
      "translated_word": "怪物",
      "display_order": 1
    }
  ]
}